requirements-tools.txt
ReadMe.md
mllint/__main__.py
mllint/__init__.py
mllint/cli.py
mllint/mllint-exe
mllint-0.12.2.dist-info/WHEEL
mllint-0.12.2.dist-info/RECORD
mllint-0.12.2.dist-info/METADATA
mllint-0.12.2.dist-info/entry_points.txt
mllint-0.12.2.dist-info/top_level.txt
