Metadata-Version: 2.1
Name: mllint
Version: 0.12.2
Summary: Software Quality Linter for Machine Learning projects
Home-page: https://github.com/bvobart/mllint
Author: Bart van Oort
Author-email: bart@vanoort.is
License: GPLv3
Project-URL: Bug Tracker, https://github.com/bvobart/mllint/issues
Platform: UNKNOWN
Classifier: Development Status :: 3 - Alpha
Classifier: Environment :: Console
Classifier: Intended Audience :: Developers
Classifier: Intended Audience :: Information Technology
Classifier: Intended Audience :: Science/Research
Classifier: License :: OSI Approved :: GNU General Public License v3 (GPLv3)
Classifier: Natural Language :: English
Classifier: Operating System :: MacOS
Classifier: Operating System :: Microsoft :: Windows
Classifier: Operating System :: POSIX :: Linux
Classifier: Programming Language :: Python :: 3
Classifier: Programming Language :: Python :: 3 :: Only
Classifier: Programming Language :: Python :: 3.6
Classifier: Programming Language :: Python :: 3.7
Classifier: Programming Language :: Python :: 3.8
Classifier: Programming Language :: Python :: 3.9
Classifier: Programming Language :: Python :: 3.10
Classifier: Topic :: Scientific/Engineering :: Artificial Intelligence
Classifier: Topic :: Scientific/Engineering :: Information Analysis
Classifier: Topic :: Software Development :: Build Tools
Classifier: Topic :: Software Development :: Pre-processors
Classifier: Topic :: Software Development :: Quality Assurance
Classifier: Topic :: Software Development :: Version Control :: Git
Requires-Python: >=3.6
Provides-Extra: tools
Requires-Dist: dvc (>=2.0.0) ; extra == 'tools'
Requires-Dist: pylint (>=2.0.0) ; extra == 'tools'
Requires-Dist: mypy (>=0.800) ; extra == 'tools'
Requires-Dist: black (>=21.4b0) ; extra == 'tools'
Requires-Dist: isort (>=5.0.0) ; extra == 'tools'
Requires-Dist: bandit (>=1.6.2) ; extra == 'tools'
